fasthx-3.1.0.dist-info/METADATA
fasthx-3.1.0.dist-info/WHEEL
fasthx-3.1.0.dist-info/entry_points.txt
fasthx-3.1.0.dist-info/licenses/LICENSE
fasthx/__init__.py
fasthx/component_selectors.py
fasthx/core_decorators.py
fasthx/dependencies.py
fasthx/htmy.py
fasthx/jinja.py
fasthx/py.typed
fasthx/typing.py
fasthx/utils.py
fasthx-3.1.0.dist-info/RECORD
