Metadata-Version: 2.4
Name: fasthx
Version: 3.1.0
Summary: FastAPI server-side rendering with built-in HTMX support.
Author-Email: Peter Volf <do.volfp@gmail.com>
License-Expression: MIT
Requires-Python: >=3.10
Requires-Dist: fastapi>=0.100.0
Provides-Extra: htmy
Requires-Dist: htmy[lxml]>=0.10.1; extra == "htmy"
Provides-Extra: jinja
Requires-Dist: jinja2<4,>=3.0.0; extra == "jinja"
